pylustrator/QLinkableWidgets.py
pylustrator/QtGui.py
pylustrator/QtGuiDrag.py
pylustrator/QtShortCuts.py
pylustrator/__init__.py
pylustrator/arc2bez.py
pylustrator/ax_rasterisation.py
pylustrator/change_tracker.py
pylustrator/components/__init__.py
pylustrator/components/align.py
pylustrator/components/figure_previews.py
pylustrator/components/info_dialog.py
pylustrator/components/matplotlibwidget.py
pylustrator/components/plot_layout.py
pylustrator/components/qitem_properties.py
pylustrator/components/qpos_and_size.py
pylustrator/components/tree_view.py
pylustrator/drag_helper.py
pylustrator/exception_swallower.py
pylustrator/helper_functions.py
pylustrator/icons/arrow.png
pylustrator/icons/bottom_y.png
pylustrator/icons/center_x.png
pylustrator/icons/center_y.png
pylustrator/icons/distribute_x.png
pylustrator/icons/distribute_y.png
pylustrator/icons/group.png
pylustrator/icons/left_x.png
pylustrator/icons/legend_icon_borderpad.png
pylustrator/icons/legend_icon_columnspacing.png
pylustrator/icons/legend_icon_fontsize.png
pylustrator/icons/legend_icon_handlelength.png
pylustrator/icons/legend_icon_handletextpad.png
pylustrator/icons/legend_icon_labelspacing.png
pylustrator/icons/legend_icon_markerscale.png
pylustrator/icons/legend_icon_title_fontsize.png
pylustrator/icons/logo.ico
pylustrator/icons/logo.png
pylustrator/icons/right_x.png
pylustrator/icons/ticks.ico
pylustrator/icons/ticks_y.ico
pylustrator/icons/top_y.png
pylustrator/jupyter_cells.py
pylustrator/lab_colormap.py
pylustrator/parse_svg.py
pylustrator/pyjack.py
pylustrator/snap.py
pylustrator-1.3.0.dist-info/LICENSE
pylustrator-1.3.0.dist-info/METADATA
pylustrator-1.3.0.dist-info/WHEEL
pylustrator-1.3.0.dist-info/RECORD
