Metadata-Version: 2.1
Name: pylustrator
Version: 1.3.0
Summary: Adds interactivity to arrange panels in matplotlib.
Home-page: https://github.com/rgerum/pylustrator
License: GPLv3
Author: rgerum
Author-email: 14153051+rgerum@users.noreply.github.com
Requires-Python: >=3.8,<4.0
Classifier: License :: Other/Proprietary License
Classifier: Programming Language :: Python :: 3
Classifier: Programming Language :: Python :: 3.8
Classifier: Programming Language :: Python :: 3.9
Classifier: Programming Language :: Python :: 3.10
Classifier: Programming Language :: Python :: 3.11
Requires-Dist: PyQt5 (>=5.6)
Requires-Dist: matplotlib (>=2.0.2)
Requires-Dist: natsort (>=2.0.0)
Requires-Dist: numpy (>=1.0.3)
Requires-Dist: qtawesome (>=0.5.0)
Requires-Dist: scikit-image (>=0.7.0)
Project-URL: Repository, https://github.com/rgerum/pylustrator
